{
  "navItems": [
    {
      "displayName": "Store",
      "queryParams": null
    },
    {
      "displayName": "Phones",
      "queryParams": {
        "category": "phones"
      }
    },
    {
      "displayName": "Laptops",
      "queryParams": {
        "category": "laptops"
      }
    },
    {
      "displayName": "Monitors",
      "queryParams": {
        "category": "monitors"
      }
    },
    {
      "displayName": "Accessories",
      "queryParams": {
        "category": "accessories"
      }
    },
    {
      "displayName": "Support",
      "path": "support",
      "queryParams": null
    }
  ]
}
